tables/__init__.py
python_tables_lib-1.0.0.dist-info/LICENSE
python_tables_lib-1.0.0.dist-info/METADATA
python_tables_lib-1.0.0.dist-info/WHEEL
python_tables_lib-1.0.0.dist-info/top_level.txt
python_tables_lib-1.0.0.dist-info/RECORD
