Metadata-Version: 2.1
Name: python-tables-lib
Version: 1.0.0
Summary: A Python lib that makes creating tables easier than ever !
Home-page: https://github.com/megat69/Lib_Tables
Author: megat69
License: UNKNOWN
Project-URL: Bug Tracker, https://github.com/megat69/Lib_Tables/issues
Platform: UNKNOWN
Classifier: Programming Language :: Python :: 3
Classifier: License :: OSI Approved :: GNU Affero General Public License v3
Classifier: Operating System :: OS Independent
Requires-Python: >=3.6
License-File: LICENSE
